supercat/classes.py
supercat/core.py
supercat/main.py
supercat/utils.py
supercat/version.txt
supercat/assets/board.png
supercat/assets/circle.png
supercat/assets/circle_big.png
supercat/assets/game.png
supercat/assets/octo_big.png
supercat/assets/square.png
supercat/assets/square_big.png
supercat/players/depressed.py
supercat/players/drunk.py
supercat/players/human.py
supercat/players/lucky.py
supercat/players/meta.py
supercat/players/murder.py
supercat/players/ordered.py
supercat-1.3.1.dist-info/METADATA
supercat-1.3.1.dist-info/RECORD
supercat-1.3.1.dist-info/WHEEL
supercat-1.3.1.dist-info/entry_points.txt
supercat-1.3.1.dist-info/top_level.txt
