Metadata-Version: 2.1
Name: supercat
Version: 1.3.1
Summary: Librería y réferi para el juego de gato anidado
Home-page: https://github.com/categulario/supercat
Author: Abraham Toriz Cruz
Author-email: categulario@gmail.com
License: MIT
Keywords: tictactoe,gato,ultimate tictactoe
Platform: UNKNOWN
Classifier: Development Status :: 4 - Beta
Classifier: Intended Audience :: Developers
Classifier: Topic :: Software Development :: Libraries :: Python Modules
Classifier: License :: OSI Approved :: MIT License
Classifier: Programming Language :: Python :: 3
Classifier: Programming Language :: Python :: 3.6
Provides-Extra: test
Requires-Dist: pygame
Provides-Extra: test
Requires-Dist: pytest; extra == 'test'
Requires-Dist: flake8; extra == 'test'
